janis_pipelines/__init__.py
janis_pipelines/__meta__.py
janis_pipelines/exportall.py
janis_pipelines/alignment/__init__.py
janis_pipelines/alignment/alignment.py
janis_pipelines/alignment/alignment_qc.py
janis_pipelines/reference/__init__.py
janis_pipelines/rnaseq_fusion/__init__.py
janis_pipelines/rnaseq_fusion/rnaseqfusion.py
janis_pipelines/rnaseq_gene_expression_quantification/__init__.py
janis_pipelines/rnaseq_gene_expression_quantification/rnaseqgeneexpressionquantification.py
janis_pipelines/rnaseq_gene_expression_quantification/rnaseqgeneexpressionquantification_inbatch.py
janis_pipelines/rnaseq_gene_expression_quantification/rnaseqgeneexpressionquantification_withqc.py
janis_pipelines/wgs_germline/__init__.py
janis_pipelines/wgs_germline/wgsgermline.py
janis_pipelines/wgs_germline/wgsgermline_variantsonly.py
janis_pipelines/wgs_germline_gatk/__init__.py
janis_pipelines/wgs_germline_gatk/wgsgermlinegatk.py
janis_pipelines/wgs_germline_gatk/wgsgermlinegatk_variantsonly.py
janis_pipelines/wgs_somatic/__init__.py
janis_pipelines/wgs_somatic/wgssomatic.py
janis_pipelines/wgs_somatic/wgssomatic_variantsonly.py
janis_pipelines/wgs_somatic_gatk/__init__.py
janis_pipelines/wgs_somatic_gatk/wgssomaticgatk.py
janis_pipelines/wgs_somatic_gatk/wgssomaticgatk_variantsonly.py
janis_pipelines.pipelines-0.13.0.dist-info/LICENSE
janis_pipelines.pipelines-0.13.0.dist-info/METADATA
janis_pipelines.pipelines-0.13.0.dist-info/WHEEL
janis_pipelines.pipelines-0.13.0.dist-info/entry_points.txt
janis_pipelines.pipelines-0.13.0.dist-info/top_level.txt
janis_pipelines.pipelines-0.13.0.dist-info/RECORD
