Metadata-Version: 2.1
Name: janis-pipelines.pipelines
Version: 0.13.0
Summary: Bioinformatics tools for Janis; the Pipeline creation helper
Home-page: https://github.com/PMCC-BioinformaticsCore/janis-pipelines
Author: Michael Franklin
Author-email: michael.franklin@petermac.org
License: GNU
Platform: UNKNOWN
Classifier: Development Status :: 2 - Pre-Alpha
Classifier: Intended Audience :: Developers
Classifier: Intended Audience :: Science/Research
Classifier: Topic :: Scientific/Engineering :: Bio-Informatics
Requires-Dist: janis-pipelines.unix >=0.10.0
Provides-Extra: ci
Requires-Dist: keyring ==21.4.0 ; extra == 'ci'
Requires-Dist: setuptools ; extra == 'ci'
Requires-Dist: wheel ; extra == 'ci'
Requires-Dist: twine ; extra == 'ci'
